optima/.env
optima/__init__.py
optima/cli.py
optima/config.py
optima/constants.py
optima/commands/__init__.py
optima/commands/op_create.py
optima/commands/op_download.py
optima/commands/op_upload.py
optima/commands/op_utils.py
optima/commands/op_view.py
optima/services/__init__.py
optima/services/api_client.py
optima/services/cli_handler.py
optima/services/cli_messages.py
optima/services/cli_prompts.py
optima/services/cli_validation.py
optima/services/db_services.py
optima/services/mf_upload.py
optima/services/mf_utils.py
optima/unimelb-mf-clients-0.7.8/bin/unix/aterm
optima/unimelb-mf-clients-0.7.8/bin/unix/aterm-download
optima/unimelb-mf-clients-0.7.8/bin/unix/aterm-gui
optima/unimelb-mf-clients-0.7.8/bin/unix/aterm-import
optima/unimelb-mf-clients-0.7.8/bin/unix/download-id-shell-script-url-create
optima/unimelb-mf-clients-0.7.8/bin/unix/download-namespace-shell-script-url-create
optima/unimelb-mf-clients-0.7.8/bin/unix/file-list
optima/unimelb-mf-clients-0.7.8/bin/unix/instrument-upload-list
optima/unimelb-mf-clients-0.7.8/bin/unix/instrument-upload-missing-find
optima/unimelb-mf-clients-0.7.8/bin/unix/scp-get
optima/unimelb-mf-clients-0.7.8/bin/unix/scp-put
optima/unimelb-mf-clients-0.7.8/bin/unix/sftp-get
optima/unimelb-mf-clients-0.7.8/bin/unix/sftp-put
optima/unimelb-mf-clients-0.7.8/bin/unix/unimelb-mf-archive
optima/unimelb-mf-clients-0.7.8/bin/unix/unimelb-mf-check
optima/unimelb-mf-clients-0.7.8/bin/unix/unimelb-mf-download
optima/unimelb-mf-clients-0.7.8/bin/unix/unimelb-mf-import-archive
optima/unimelb-mf-clients-0.7.8/bin/unix/unimelb-mf-instrument-upload
optima/unimelb-mf-clients-0.7.8/bin/unix/unimelb-mf-perf
optima/unimelb-mf-clients-0.7.8/bin/unix/unimelb-mf-upload
optima/unimelb-mf-clients-0.7.8/bin/unix/facility/facility-download-aterm-script-url-create
optima/unimelb-mf-clients-0.7.8/bin/unix/facility/facility-download-shell-script-url-create
optima/unimelb-mf-clients-0.7.8/bin/unix/module/unimelb-mf-clients-current
optima_cli-1.0.4.dist-info/METADATA
optima_cli-1.0.4.dist-info/WHEEL
optima_cli-1.0.4.dist-info/entry_points.txt
optima_cli-1.0.4.dist-info/top_level.txt
optima_cli-1.0.4.dist-info/RECORD
